Topsis_Paras_101916051/__init__.py
Topsis_Paras_101916051/topsis.py
Topsis_Paras_101916051-0.0.1.dist-info/LICENSE
Topsis_Paras_101916051-0.0.1.dist-info/METADATA
Topsis_Paras_101916051-0.0.1.dist-info/WHEEL
Topsis_Paras_101916051-0.0.1.dist-info/entry_points.txt
Topsis_Paras_101916051-0.0.1.dist-info/top_level.txt
Topsis_Paras_101916051-0.0.1.dist-info/RECORD
