Metadata-Version: 2.1
Name: Topsis-Paras-101916051
Version: 0.0.1
Summary: A package -> Calculates Topsis Score and Rank them accordingly
Home-page: https://github.com/Paras-Sood/Topsis_Paras_101916051
Author: Paras Sood
Author-email: paras29sood@gmail.com
License: MIT
Platform: UNKNOWN
Classifier: Programming Language :: Python :: 3
Classifier: License :: OSI Approved :: MIT License
Classifier: Operating System :: OS Independent
License-File: LICENSE
Requires-Dist: pandas
Requires-Dist: numpy
